{
    "id": 127633870,
    "name": "ledinis kalnas",
    "author": "S3N1",
    "creators": ["S3N1"],
    "verifier": "S3N1",
    "verification": "https://www.youtube.com/watch?v=QAml95fXl68",
       "records": [

        {
          "user": "hextorus",
          "enjoyment": 6
        },
        {
          "user": "NojusGaminGG",
          "enjoyment": 6
        },
        {
          "user": "danz",
          "enjoyment": 8
        },
        {
          "user": "ta1p",
          "enjoyment": 6
        }

    ]


}